CHANGELOG.txt
LICENSE.txt
MANIFEST.in
README.md
requirements.txt
setup.py
EnsembleArgumentationBasic/EnsembleArgument.py
EnsembleArgumentationBasic/__init__.py
Enssembleargumentationbasic.egg-info/PKG-INFO
Enssembleargumentationbasic.egg-info/SOURCES.txt
Enssembleargumentationbasic.egg-info/dependency_links.txt
Enssembleargumentationbasic.egg-info/top_level.txt