Metadata-Version: 1.2
Name: Enssembleargumentationbasic
Version: 0.0.1
Summary: A basic argumentation process where the outcomes from different models can argue for generating a final output.
Home-page: UNKNOWN
Author: Istiak Ahmed
Author-email: istiak.uiu.bd@gmail.com
License: MIT
Project-URL: Code, https://github.com/Istiak1992/BasicEnsembleArgumentation/
Platform: UNKNOWN
Classifier: Development Status :: 5 - Production/Stable
Classifier: Intended Audience :: Education
Classifier: Operating System :: Microsoft :: Windows :: Windows 10
Classifier: License :: OSI Approved :: MIT License
Classifier: Programming Language :: Python :: 3
Requires-Python: >=3.8
